<annotation>
    <folder>batch5</folder>
    <filename>image_439.png</filename>
    <size>
        <width>180</width>
        <height>320</height>
        <depth>3</depth>
    </size>
    <object>
        <name>i pipe</name>
        <difficult>0</difficult>
        <bndbox>
            <xmin>20</xmin>
            <ymin>217</ymin>
            <xmax>132</xmax>
            <ymax>259</ymax>
        </bndbox>
    </object>
    <object>
        <name>Back</name>
        <difficult>0</difficult>
        <bndbox>
            <xmin>24</xmin>
            <ymin>45</ymin>
            <xmax>180</xmax>
            <ymax>211</ymax>
        </bndbox>
    </object>
</annotation>